rftool/__init__.py
rftool/pcb.py
rftool/radar.py
rftool/utility.py
rf_tool-0.0.10.dist-info/LICENSE
rf_tool-0.0.10.dist-info/METADATA
rf_tool-0.0.10.dist-info/WHEEL
rf_tool-0.0.10.dist-info/top_level.txt
rf_tool-0.0.10.dist-info/RECORD
